LICENSE
capture_stream/__init__.py
capture_stream/__main__.py
capture_stream/py.typed
capture_stream-0.0.1.5.dist-info/LICENSE
capture_stream-0.0.1.5.dist-info/METADATA
capture_stream-0.0.1.5.dist-info/WHEEL
capture_stream-0.0.1.5.dist-info/entry_points.txt
capture_stream-0.0.1.5.dist-info/RECORD
