Metadata-Version: 2.1
Name: capture_stream
Version: 0.0.1.5
Summary: Capture video stream, save as screenshots.
Home-page: https://github.com/ChenyangGao/web-mount-packs/tree/main/python-module/capture_stream
License: MIT
Keywords: video,stream,capture
Author: ChenyangGao
Author-email: wosiwujm@gmail.com
Requires-Python: >=3.9,<4.0
Classifier: Development Status :: 5 - Production/Stable
Classifier: Intended Audience :: Developers
Classifier: License :: OSI Approved :: MIT License
Classifier: Operating System :: OS Independent
Classifier: Programming Language :: Python
Classifier: Programming Language :: Python :: 3
Classifier: Programming Language :: Python :: 3.9
Classifier: Programming Language :: Python :: 3.10
Classifier: Programming Language :: Python :: 3.11
Classifier: Programming Language :: Python :: 3.12
Classifier: Programming Language :: Python :: 3 :: Only
Classifier: Topic :: Software Development
Classifier: Topic :: Software Development :: Libraries
Classifier: Topic :: Software Development :: Libraries :: Python Modules
Requires-Dist: opencv-python
Project-URL: Repository, https://github.com/ChenyangGao/web-mount-packs/tree/main/python-module/capture_stream
